bytewax/interval/__init__.py
bytewax/interval/py.typed
bytewax_interval-0.1.dist-info/LICENSE.md
bytewax_interval-0.1.dist-info/METADATA
bytewax_interval-0.1.dist-info/WHEEL
bytewax_interval-0.1.dist-info/top_level.txt
bytewax_interval-0.1.dist-info/RECORD
