Metadata-Version: 2.1
Name: bytewax-interval
Version: 0.1
Summary: Interval join operator for Bytewax
Author-email: "Bytewax, Inc." <info@bytewax.io>
License: # Software License Agreement
Project-URL: Homepage, https://github.com/bytewax/bytewax-interval
Project-URL: Bug Reports, https://github.com/bytewax/bytewax-interval/issues/new
Project-URL: Source, https://github.com/bytewax/bytewax-interval/
Keywords: bytewax,streaming,operator
Classifier: Development Status :: 4 - Beta
Classifier: Intended Audience :: Developers
Classifier: Programming Language :: Python :: 3
Classifier: Programming Language :: Python :: 3.9
Classifier: Programming Language :: Python :: 3.10
Classifier: Programming Language :: Python :: 3.11
Classifier: Programming Language :: Python :: 3.12
Classifier: Programming Language :: Python :: 3 :: Only
Requires-Python: >=3.9
License-File: LICENSE.md
Requires-Dist: bytewax>=0.21
